composition/__init__.py
composition/composition.py
composition/test/test.py
python_composition-0.1.0.dist-info/LICENSE
python_composition-0.1.0.dist-info/METADATA
python_composition-0.1.0.dist-info/WHEEL
python_composition-0.1.0.dist-info/RECORD
