Metadata-Version: 2.1
Name: python-composition
Version: 0.1.0
Summary: Add composition and applying operators to python.
License: AGPL 3.0
Author: eyalk5
Requires-Python: >=3.10,<4.0
Classifier: License :: Other/Proprietary License
Classifier: Programming Language :: Python :: 3
Classifier: Programming Language :: Python :: 3.10
Classifier: Programming Language :: Python :: 3.11
Requires-Dist: multimethod (>=1.10,<2.0)
Requires-Dist: sspipe
